UCube/__init__.py
UCube/error.py
UCube/objects.py
UCube/ucubeasync.py
UCube/ucubeclient.py
UCube/ucubesync.py
UCube/models/__init__.py
UCube/models/base.py
UCube/models/board.py
UCube/models/club.py
UCube/models/comment.py
UCube/models/image.py
UCube/models/notification.py
UCube/models/post.py
UCube/models/user.py
UCube/models/video.py
UCube-0.0.2.2.dist-info/LICENSE
UCube-0.0.2.2.dist-info/METADATA
UCube-0.0.2.2.dist-info/WHEEL
UCube-0.0.2.2.dist-info/top_level.txt
UCube-0.0.2.2.dist-info/RECORD
