Metadata-Version: 2.1
Name: UCube
Version: 0.0.2.2
Summary: Creates internal cache for the communities a user follows on united-cube.com
Home-page: https://github.com/MujyKun/united-cube/
Author: MujyKun
Author-email: mujy@irenebot.com
License: MIT License
Platform: UNKNOWN
Classifier: Development Status :: 5 - Production/Stable
Classifier: License :: OSI Approved :: MIT License
Classifier: Programming Language :: Python
Requires-Python: >=3.7
Requires-Dist: aiohttp (>=3.6.2)
Requires-Dist: requests (>=2.22.0)
